{
  "date": "2026-06-14",
  "created_at": "2026-06-14T00:00:10.509663",
  "crossings": [
    {
      "event_id": "314452",
      "title": "Bank of Mexico Decision in June",
      "slug": "bank-of-mexico-decision-in-june",
      "prev_prob": 0.9075,
      "curr_prob": 0.8905,
      "threshold": 0.9,
      "direction": "down",
      "time": "06:00",
      "timestamp": "2026-06-14T06:00:18.316699"
    },
    {
      "event_id": "314452",
      "title": "Bank of Mexico Decision in June",
      "slug": "bank-of-mexico-decision-in-june",
      "prev_prob": 0.8905,
      "curr_prob": 0.9055,
      "threshold": 0.9,
      "direction": "up",
      "time": "07:00",
      "timestamp": "2026-06-14T07:00:17.454205"
    },
    {
      "event_id": "231170",
      "title": "Bank of England rate hike in 2026?",
      "slug": "bank-of-england-rate-hike-in-2026",
      "prev_prob": 0.7,
      "curr_prob": 0.695,
      "threshold": 0.7,
      "direction": "down",
      "time": "12:00",
      "timestamp": "2026-06-14T12:00:33.816279"
    },
    {
      "event_id": "231170",
      "title": "Bank of England rate hike in 2026?",
      "slug": "bank-of-england-rate-hike-in-2026",
      "prev_prob": 0.695,
      "curr_prob": 0.7,
      "threshold": 0.7,
      "direction": "up",
      "time": "13:00",
      "timestamp": "2026-06-14T13:00:34.577844"
    },
    {
      "event_id": "231170",
      "title": "Bank of England rate hike in 2026?",
      "slug": "bank-of-england-rate-hike-in-2026",
      "prev_prob": 0.7,
      "curr_prob": 0.695,
      "threshold": 0.7,
      "direction": "down",
      "time": "14:00",
      "timestamp": "2026-06-14T14:00:30.998652"
    },
    {
      "event_id": "290152",
      "title": "Tech Layoffs Up or Down in 20​26?",
      "slug": "tech-layoffs-up-or-down-in-2026",
      "prev_prob": 0.9,
      "curr_prob": 0.895,
      "threshold": 0.9,
      "direction": "down",
      "time": "22:00",
      "timestamp": "2026-06-14T22:00:35.182870"
    }
  ],
  "crossing_count": 6,
  "last_updated": "2026-06-14T22:00:35.183174"
}