{
  "timestamp": "2026-06-22T01:01:20.161002",
  "events": {
    "48802": {
      "prob": 0.125
    },
    "51456": {
      "prob": 0.8035
    },
    "57711": {
      "prob": 0.987
    },
    "68544": {
      "prob": 0.35
    },
    "73145": {
      "prob": 0.075
    },
    "75598": {
      "prob": 0.175
    },
    "75684": {
      "prob": 0.013
    },
    "79041": {
      "prob": 0.0075
    },
    "79048": {
      "prob": 0.6165
    },
    "79049": {
      "prob": 0.0685
    },
    "79050": {
      "prob": 0.0085
    },
    "79056": {
      "prob": 0.43
    },
    "79061": {
      "prob": 0.045
    },
    "79067": {
      "prob": 0.085
    },
    "79079": {
      "prob": 0.04
    },
    "79080": {
      "prob": 0.82
    },
    "79090": {
      "prob": 0.0045
    },
    "79124": {
      "prob": 0.085
    },
    "83771": {
      "prob": 0.0485
    },
    "85784": {
      "prob": 0.0025
    },
    "86448": {
      "prob": 0.046
    },
    "96053": {
      "prob": 0.11
    },
    "103418": {
      "prob": 0.38
    },
    "106260": {
      "prob": 0.0065
    },
    "117916": {
      "prob": 0.044
    },
    "133436": {
      "prob": 0.005
    },
    "145689": {
      "prob": 0.058
    },
    "154155": {
      "prob": 0.0075
    },
    "161717": {
      "prob": 0.365
    },
    "164439": {
      "prob": 0.095
    },
    "169319": {
      "prob": 0.005
    },
    "191709": {
      "prob": 0.18
    },
    "192873": {
      "prob": 0.265
    },
    "192925": {
      "prob": 0.005
    },
    "193337": {
      "prob": 0.88
    },
    "193867": {
      "prob": 0.755
    },
    "194017": {
      "prob": 0.255
    },
    "194023": {
      "prob": 0.0495
    },
    "197681": {
      "prob": 0.055
    },
    "197806": {
      "prob": 0.075
    },
    "200252": {
      "prob": 0.0185
    },
    "228549": {
      "prob": 0.1945
    },
    "228565": {
      "prob": 0.22
    },
    "280935": {
      "prob": 0.19
    },
    "290152": {
      "prob": 0.895
    },
    "340178": {
      "prob": 0.0035
    },
    "358902": {
      "prob": 0.0255
    },
    "407910": {
      "prob": 0.063
    },
    "428400": {
      "prob": 0.43
    },
    "452365": {
      "prob": 0.067
    },
    "488818": {
      "prob": 0.007
    },
    "488841": {
      "prob": 0.012
    },
    "507193": {
      "prob": 0.16
    },
    "528229": {
      "prob": 0.0255
    },
    "528463": {
      "prob": 0.2485
    },
    "528479": {
      "prob": 0.125
    },
    "548898": {
      "prob": 0.0405
    },
    "577704": {
      "prob": 0.036
    },
    "69702": {
      "prob": 0.0065
    },
    "73078": {
      "prob": 0.0325
    },
    "73131": {
      "prob": 0.105
    },
    "73331": {
      "prob": 0.0285
    },
    "73338": {
      "prob": 0.16
    },
    "79137": {
      "prob": 0.06
    },
    "80660": {
      "prob": 0.085
    },
    "84803": {
      "prob": 0.037
    },
    "90394": {
      "prob": 0.0075
    },
    "101936": {
      "prob": 0.605
    },
    "118468": {
      "prob": 0.135
    },
    "137182": {
      "prob": 0.3865
    },
    "138976": {
      "prob": 0.108
    },
    "147795": {
      "prob": 0.031
    },
    "148423": {
      "prob": 0.066
    },
    "150178": {
      "prob": 0.056
    },
    "150199": {
      "prob": 0.087
    },
    "181671": {
      "prob": 0.0055
    },
    "182146": {
      "prob": 0.135
    },
    "183657": {
      "prob": 0.2365
    },
    "185883": {
      "prob": 0.0025
    },
    "185924": {
      "prob": 0.0145
    },
    "189770": {
      "prob": 0.0675
    },
    "197077": {
      "prob": 0.14
    },
    "197683": {
      "prob": 0.485
    },
    "200713": {
      "prob": 0.039
    },
    "201560": {
      "prob": 0.0315
    },
    "201624": {
      "prob": 0.1555
    },
    "226397": {
      "prob": 0.185
    },
    "230330": {
      "prob": 0.045
    },
    "231170": {
      "prob": 0.465
    },
    "250371": {
      "prob": 0.009
    },
    "261337": {
      "prob": 0.405
    },
    "287395": {
      "prob": 0.785
    },
    "314452": {
      "prob": 0.9695
    },
    "326352": {
      "prob": 0.1
    },
    "339867": {
      "prob": 0.75
    },
    "357856": {
      "prob": 0.835
    },
    "375597": {
      "prob": 0.065
    },
    "375801": {
      "prob": 0.0015
    },
    "379551": {
      "prob": 0.0315
    },
    "390159": {
      "prob": 0.003
    },
    "427800": {
      "prob": 0.065
    },
    "428185": {
      "prob": 0.004
    },
    "431896": {
      "prob": 0.01
    },
    "431911": {
      "prob": 0.004
    },
    "434804": {
      "prob": 0.0005
    },
    "455867": {
      "prob": 0.405
    },
    "455875": {
      "prob": 0.875
    },
    "474889": {
      "prob": 0.0455
    },
    "481717": {
      "prob": 0.0115
    },
    "506697": {
      "prob": 0.0155
    },
    "527954": {
      "prob": 0.0005
    },
    "528306": {
      "prob": 0.031
    },
    "528422": {
      "prob": 0.025
    },
    "535176": {
      "prob": 0.0165
    },
    "535607": {
      "prob": 0.4425
    },
    "580294": {
      "prob": 0.0115
    }
  }
}