{
  "timestamp": "2026-05-09T01:01:28.998000",
  "events": {
    "48802": {
      "prob": 0.225
    },
    "51456": {
      "prob": 0.5565
    },
    "57711": {
      "prob": 0.825
    },
    "68544": {
      "prob": 0.18
    },
    "73145": {
      "prob": 0.115
    },
    "75598": {
      "prob": 0.205
    },
    "75605": {
      "prob": 0.375
    },
    "75684": {
      "prob": 0.0315
    },
    "79041": {
      "prob": 0.0075
    },
    "79048": {
      "prob": 0.542
    },
    "79049": {
      "prob": 0.0505
    },
    "79050": {
      "prob": 0.0335
    },
    "79056": {
      "prob": 0.4
    },
    "79061": {
      "prob": 0.115
    },
    "79067": {
      "prob": 0.08
    },
    "79079": {
      "prob": 0.1195
    },
    "79080": {
      "prob": 0.225
    },
    "79090": {
      "prob": 0.0035
    },
    "79124": {
      "prob": 0.135
    },
    "83771": {
      "prob": 0.08
    },
    "86448": {
      "prob": 0.0515
    },
    "96053": {
      "prob": 0.13
    },
    "98133": {
      "prob": 0.75
    },
    "103418": {
      "prob": 0.315
    },
    "106260": {
      "prob": 0.075
    },
    "117916": {
      "prob": 0.13
    },
    "123568": {
      "prob": 0.485
    },
    "133436": {
      "prob": 0.0105
    },
    "145689": {
      "prob": 0.0565
    },
    "154155": {
      "prob": 0.0115
    },
    "161717": {
      "prob": 0.365
    },
    "164439": {
      "prob": 0.205
    },
    "169319": {
      "prob": 0.009
    },
    "190776": {
      "prob": 0.498
    },
    "191709": {
      "prob": 0.31
    },
    "192873": {
      "prob": 0.175
    },
    "192925": {
      "prob": 0.0305
    },
    "193319": {
      "prob": 0.978
    },
    "193337": {
      "prob": 0.72
    },
    "193867": {
      "prob": 0.675
    },
    "194017": {
      "prob": 0.0805
    },
    "194023": {
      "prob": 0.369
    },
    "197681": {
      "prob": 0.22
    },
    "197806": {
      "prob": 0.07
    },
    "198615": {
      "prob": 0.255
    },
    "200252": {
      "prob": 0.13
    },
    "228549": {
      "prob": 0.0695
    },
    "228565": {
      "prob": 0.46
    },
    "280935": {
      "prob": 0.57
    },
    "290152": {
      "prob": 0.78
    },
    "333286": {
      "prob": 0.695
    },
    "340178": {
      "prob": 0.1145
    },
    "354833": {
      "prob": 0.0135
    },
    "358902": {
      "prob": 0.054
    },
    "385367": {
      "prob": 0.845
    },
    "385555": {
      "prob": 0.006
    },
    "385556": {
      "prob": 0.0035
    },
    "385557": {
      "prob": 0.858
    },
    "404066": {
      "prob": 0.0405
    },
    "404244": {
      "prob": 0.25
    },
    "407910": {
      "prob": 0.133
    },
    "431320": {
      "prob": 0.375
    },
    "452365": {
      "prob": 0.1405
    },
    "69702": {
      "prob": 0.0165
    },
    "73078": {
      "prob": 0.0395
    },
    "73131": {
      "prob": 0.135
    },
    "73331": {
      "prob": 0.05
    },
    "79137": {
      "prob": 0.0965
    },
    "80660": {
      "prob": 0.0395
    },
    "80773": {
      "prob": 0.755
    },
    "84803": {
      "prob": 0.0435
    },
    "90394": {
      "prob": 0.0065
    },
    "101772": {
      "prob": 0.0165
    },
    "101936": {
      "prob": 0.18
    },
    "106884": {
      "prob": 0.025
    },
    "118455": {
      "prob": 0.84
    },
    "118468": {
      "prob": 0.13
    },
    "137182": {
      "prob": 0.126
    },
    "138976": {
      "prob": 0.335
    },
    "147795": {
      "prob": 0.052
    },
    "148423": {
      "prob": 0.09
    },
    "150178": {
      "prob": 0.0025
    },
    "162276": {
      "prob": 0.4655
    },
    "181671": {
      "prob": 0.0025
    },
    "182146": {
      "prob": 0.435
    },
    "183657": {
      "prob": 0.3835
    },
    "185883": {
      "prob": 0.0265
    },
    "185924": {
      "prob": 0.155
    },
    "189770": {
      "prob": 0.114
    },
    "197077": {
      "prob": 0.325
    },
    "197683": {
      "prob": 0.49
    },
    "200713": {
      "prob": 0.059
    },
    "201560": {
      "prob": 0.044
    },
    "201624": {
      "prob": 0.0855
    },
    "206748": {
      "prob": 0.017
    },
    "213092": {
      "prob": 0.205
    },
    "226135": {
      "prob": 0.014
    },
    "226397": {
      "prob": 0.29
    },
    "230330": {
      "prob": 0.125
    },
    "231170": {
      "prob": 0.655
    },
    "232652": {
      "prob": 0.0085
    },
    "246674": {
      "prob": 0.05
    },
    "248247": {
      "prob": 0.0025
    },
    "250371": {
      "prob": 0.0125
    },
    "287166": {
      "prob": 0.825
    },
    "287195": {
      "prob": 0.004
    },
    "287227": {
      "prob": 0.003
    },
    "287342": {
      "prob": 0.01
    },
    "287380": {
      "prob": 0.825
    },
    "287395": {
      "prob": 0.895
    },
    "301523": {
      "prob": 0.0025
    },
    "301531": {
      "prob": 0.004
    },
    "329566": {
      "prob": 0.0065
    },
    "329821": {
      "prob": 0.225
    },
    "362137": {
      "prob": 0.0185
    },
    "364599": {
      "prob": 0.0045
    },
    "364618": {
      "prob": 0.0095
    },
    "364672": {
      "prob": 0.0025
    },
    "375597": {
      "prob": 0.525
    },
    "375801": {
      "prob": 0.0145
    },
    "379514": {
      "prob": 0.875
    },
    "379551": {
      "prob": 0.0365
    },
    "407225": {
      "prob": 0.0215
    },
    "427800": {
      "prob": 0.105
    },
    "431398": {
      "prob": 0.48
    },
    "432066": {
      "prob": 0.036
    },
    "432180": {
      "prob": 0.67
    },
    "435097": {
      "prob": 0.21
    }
  }
}