{
  "events": {
    "75515": {
      "id": "75515",
      "title": "Will Lionel Messi play in the 2026 FIFA World Cup?",
      "slug": "will-lionel-messi-play-in-the-2026-fifa-world-cup",
      "url": "https://polymarket.com/event/will-lionel-messi-play-in-the-2026-fifa-world-cup",
      "probability": 0.935,
      "option_text": "Yes",
      "tags": [
        "pop-culture",
        "soccer",
        "world",
        "celebrities",
        "sports",
        "fifa-world-cup"
      ],
      "volume": 86211.12717900009,
      "liquidity": 2634.5838,
      "current_prob": 0.935,
      "added_at": "2026-05-05T15:48:24.558565",
      "first_seen": "2026-05-05T15:48:24.558565",
      "peak_prob": 0.94,
      "last_checked_prob": 0.935,
      "history": [
        {
          "time": "15:48",
          "prob": 0.93,
          "reason": "Added to Long-Term (daily update)"
        }
      ]
    },
    "108522": {
      "id": "108522",
      "title": "AI data center moratorium passed before 2027?",
      "slug": "ai-data-center-moratorium-passed-before-2027",
      "url": "https://polymarket.com/event/ai-data-center-moratorium-passed-before-2027",
      "probability": 0.9235,
      "option_text": "Yes",
      "tags": [
        "pop-culture",
        "tech",
        "politics",
        "ai",
        "bernie-sanders",
        "artificial-intelligence"
      ],
      "volume": 47755.81452399998,
      "liquidity": 10999.1322,
      "current_prob": 0.9235,
      "added_at": "2026-05-05T15:48:24.558565",
      "first_seen": "2026-05-05T15:48:24.558565",
      "peak_prob": 0.951,
      "last_checked_prob": 0.9235,
      "history": [
        {
          "time": "15:48",
          "prob": 0.9345,
          "reason": "Added to Long-Term (daily update)"
        }
      ]
    },
    "166460": {
      "id": "166460",
      "title": "Survivor 50 Winner",
      "slug": "survivor-50-winner",
      "url": "https://polymarket.com/event/survivor-50-winner",
      "probability": 0.875,
      "option_text": "Aubry Bracco",
      "tags": [
        "pop-culture",
        "reality-tv"
      ],
      "volume": 1423844.0927259997,
      "liquidity": 258724.06441,
      "current_prob": 0.875,
      "added_at": "2026-05-05T15:48:24.558565",
      "first_seen": "2026-05-05T15:48:24.558565",
      "peak_prob": 0.895,
      "last_checked_prob": 0.875,
      "history": [
        {
          "time": "15:48",
          "prob": 0.89,
          "reason": "Added to Long-Term (daily update)"
        }
      ]
    },
    "166699": {
      "id": "166699",
      "title": "Eurovision 2026: First Semi-Final",
      "slug": "eurovision-2026-first-semi-final",
      "url": "https://polymarket.com/event/eurovision-2026-first-semi-final",
      "probability": 0.9785,
      "option_text": "Israel",
      "tags": [
        "eurovision",
        "music",
        "pop-culture"
      ],
      "volume": 596429.804275,
      "liquidity": 144925.02368,
      "current_prob": 0.9785,
      "added_at": "2026-05-05T15:48:24.558565",
      "first_seen": "2026-05-05T15:48:24.558565",
      "peak_prob": 0.9895,
      "last_checked_prob": 0.9785,
      "history": [
        {
          "time": "15:48",
          "prob": 0.9695,
          "reason": "Added to Long-Term (daily update)"
        }
      ]
    },
    "401113": {
      "id": "401113",
      "title": "Who will be featured on ICEMAN?",
      "slug": "who-will-be-featured-on-iceman",
      "url": "https://polymarket.com/event/who-will-be-featured-on-iceman",
      "probability": 0.71,
      "option_text": "21 Savage",
      "tags": [
        "drake",
        "album",
        "celebrities",
        "pop-culture",
        "iceman",
        "song"
      ],
      "volume": 78347.410386,
      "liquidity": 31291.17072,
      "current_prob": 0.71,
      "added_at": "2026-05-05T15:48:24.558565",
      "first_seen": "2026-05-05T15:48:24.558565",
      "peak_prob": 0.85,
      "last_checked_prob": 0.71,
      "history": [
        {
          "time": "15:48",
          "prob": 0.805,
          "reason": "Added to Long-Term (daily update)"
        },
        {
          "time": "00:06",
          "prob": 0.71,
          "reason": "Update: 85.0% → 71.0%"
        },
        {
          "time": "00:06",
          "prob": 0.805,
          "reason": "Update: 71.0% → 80.5%"
        },
        {
          "time": "00:05",
          "prob": 0.705,
          "reason": "Update: 80.5% → 70.5%"
        }
      ]
    },
    "283618": {
      "id": "283618",
      "title": "Will Olivia Rodrigo release a new original album by...?",
      "slug": "will-olivia-rodrigo-release-a-new-original-album-by-august-31",
      "url": "https://polymarket.com/event/will-olivia-rodrigo-release-a-new-original-album-by-august-31",
      "probability": 0.988,
      "option_text": "August 31",
      "tags": [
        "song",
        "music",
        "album",
        "pop-culture"
      ],
      "volume": 13582.391846999997,
      "liquidity": 5934.19663,
      "current_prob": 0.988,
      "added_at": "2026-05-05T18:47:12.236700",
      "first_seen": "2026-05-05T18:47:12.236700",
      "peak_prob": 0.988,
      "last_checked_prob": 0.988,
      "history": [
        {
          "time": "18:47",
          "prob": 0.987,
          "reason": "Added to Long-Term (daily update)"
        }
      ]
    },
    "407521": {
      "id": "407521",
      "title": "What will be said on ICEMAN?",
      "slug": "what-will-be-said-on-iceman",
      "url": "https://polymarket.com/event/what-will-be-said-on-iceman",
      "probability": 0.835,
      "option_text": "Covid",
      "tags": [
        "celebrities",
        "song",
        "music",
        "pop-culture",
        "album",
        "mention-markets",
        "drake",
        "iceman"
      ],
      "volume": 56127.35001900003,
      "liquidity": 3395.59774,
      "current_prob": 0.835,
      "added_at": "2026-05-07T00:07:39.600229",
      "first_seen": "2026-05-07T00:07:39.600229",
      "peak_prob": 0.865,
      "last_checked_prob": 0.835,
      "history": [
        {
          "time": "00:07",
          "prob": 0.86,
          "reason": "Added to Long-Term (daily update)"
        },
        {
          "time": "00:05",
          "prob": 0.77,
          "reason": "Update: 86.5% → 77.0%"
        },
        {
          "time": "00:05",
          "prob": 0.835,
          "reason": "Update: 77.0% → 83.5%"
        }
      ]
    },
    "333162": {
      "id": "333162",
      "title": "Which characters will appear in Avengers: Doomsday?",
      "slug": "which-characters-will-appear-in-avengers-doomsday",
      "url": "https://polymarket.com/event/which-characters-will-appear-in-avengers-doomsday",
      "probability": 0.935,
      "option_text": "Hugh Jackman as Wolverine",
      "tags": [
        "movies",
        "pop-culture"
      ],
      "volume": 37098.284959000004,
      "liquidity": 13281.3487,
      "current_prob": 0.935,
      "added_at": "2026-05-09T00:06:36.502824",
      "first_seen": "2026-05-09T00:06:36.502824",
      "peak_prob": 0.935,
      "last_checked_prob": 0.935,
      "history": [
        {
          "time": "00:06",
          "prob": 0.71,
          "reason": "Added to Long-Term (daily update)"
        },
        {
          "time": "00:05",
          "prob": 0.935,
          "reason": "Update: 74.0% → 93.5%"
        }
      ]
    },
    "198746": {
      "id": "198746",
      "title": "Who will win Top Chef Season 23?",
      "slug": "who-will-win-top-chef-season-23",
      "url": "https://polymarket.com/event/who-will-win-top-chef-season-23",
      "probability": 0.9025,
      "option_text": "Rhoda Magbitang",
      "tags": [
        "pop-culture",
        "reality-tv"
      ],
      "volume": 80453.74964200001,
      "liquidity": 26338.26158,
      "current_prob": 0.9025,
      "added_at": "2026-05-10T00:05:52.504234",
      "first_seen": "2026-05-10T00:05:52.504234",
      "peak_prob": 0.9415,
      "last_checked_prob": 0.9025,
      "history": [
        {
          "time": "00:05",
          "prob": 0.9415,
          "reason": "Added to Long-Term (daily update)"
        }
      ]
    },
    "452568": {
      "id": "452568",
      "title": "What will be the top US Netflix movie this week?",
      "slug": "what-will-be-the-top-us-netflix-movie-this-week-563",
      "url": "https://polymarket.com/event/what-will-be-the-top-us-netflix-movie-this-week-563",
      "probability": 0.9875,
      "option_text": "Swapped",
      "tags": [
        "netflix",
        "pop-culture",
        "top-netflix",
        "movies"
      ],
      "volume": 15200.013793,
      "liquidity": 25765.82959,
      "current_prob": 0.9875,
      "added_at": "2026-05-10T00:05:52.504234",
      "first_seen": "2026-05-10T00:05:52.504234",
      "peak_prob": 0.9875,
      "last_checked_prob": 0.9875,
      "history": [
        {
          "time": "00:05",
          "prob": 0.958,
          "reason": "Added to Long-Term (daily update)"
        }
      ]
    },
    "79103": {
      "id": "79103",
      "title": "Which artists will release a new song in 2026?",
      "slug": "which-artists-will-release-a-new-song-in-2026",
      "url": "https://polymarket.com/event/which-artists-will-release-a-new-song-in-2026",
      "probability": 0.985,
      "option_text": "Drake",
      "tags": [
        "music",
        "pop-culture"
      ],
      "volume": 108283.265174,
      "liquidity": 1940.87479,
      "current_prob": 0.985,
      "added_at": "2026-05-11T00:05:33.909317",
      "first_seen": "2026-05-11T00:05:33.909317",
      "peak_prob": 0.985,
      "last_checked_prob": 0.985,
      "history": [
        {
          "time": "00:05",
          "prob": 0.985,
          "reason": "Added to Long-Term (daily update)"
        }
      ]
    },
    "106016": {
      "id": "106016",
      "title": "Who will attend Taylor Swift and Travis Kelce's wedding?",
      "slug": "who-will-attend-taylor-swift-and-travis-kelces-wedding",
      "url": "https://polymarket.com/event/who-will-attend-taylor-swift-and-travis-kelces-wedding",
      "probability": 0.76,
      "option_text": "Danielle Haim",
      "tags": [
        "pop-culture",
        "taylor-swift",
        "nfl",
        "music"
      ],
      "volume": 253422.69134100006,
      "liquidity": 5035.42344,
      "current_prob": 0.76,
      "added_at": "2026-05-11T00:05:33.909317",
      "first_seen": "2026-05-11T00:05:33.909317",
      "peak_prob": 0.76,
      "last_checked_prob": 0.76,
      "history": [
        {
          "time": "00:05",
          "prob": 0.76,
          "reason": "Added to Long-Term (daily update)"
        }
      ]
    },
    "166704": {
      "id": "166704",
      "title": "Eurovision 2026: Second Semi-Final",
      "slug": "eurovision-2026-second-semi-final",
      "url": "https://polymarket.com/event/eurovision-2026-second-semi-final",
      "probability": 0.9805,
      "option_text": "Australia",
      "tags": [
        "eurovision",
        "music",
        "pop-culture"
      ],
      "volume": 334070.91492799995,
      "liquidity": 91070.66595,
      "current_prob": 0.9805,
      "added_at": "2026-05-11T00:05:33.909317",
      "first_seen": "2026-05-11T00:05:33.909317",
      "peak_prob": 0.9805,
      "last_checked_prob": 0.9805,
      "history": [
        {
          "time": "00:05",
          "prob": 0.9805,
          "reason": "Added to Long-Term (daily update)"
        }
      ]
    },
    "452602": {
      "id": "452602",
      "title": "What will be the top global Netflix movie this week?",
      "slug": "what-will-be-the-top-global-netflix-movie-this-week-899",
      "url": "https://polymarket.com/event/what-will-be-the-top-global-netflix-movie-this-week-899",
      "probability": 0.99,
      "option_text": "Swapped",
      "tags": [
        "pop-culture",
        "top-netflix",
        "netflix",
        "movies"
      ],
      "volume": 10896.687984999999,
      "liquidity": 21342.78101,
      "current_prob": 0.99,
      "added_at": "2026-05-11T00:05:33.909317",
      "first_seen": "2026-05-11T00:05:33.909317",
      "peak_prob": 0.99,
      "last_checked_prob": 0.99,
      "history": [
        {
          "time": "00:05",
          "prob": 0.99,
          "reason": "Added to Long-Term (daily update)"
        }
      ]
    }
  },
  "updated_at": "2026-05-11T00:05:33.909482",
  "event_count": 14
}