{
  "date": "2026-07-05",
  "created_at": "2026-07-05T00:01:00.805001",
  "crossings": [
    {
      "event_id": "211829",
      "title": "Will MrBeast get married by December 31?",
      "slug": "will-mrbeast-get-married-by-december-31",
      "prev_prob": 0.8,
      "curr_prob": 0.775,
      "threshold": 0.8,
      "direction": "down",
      "time": "14:00",
      "timestamp": "2026-07-05T14:00:44.513343"
    },
    {
      "event_id": "535925",
      "title": "Who will win Love Island USA Season 8? (Men)",
      "slug": "who-will-win-love-island-usa-season-8-men",
      "prev_prob": 0.83,
      "curr_prob": 0.76,
      "threshold": 0.8,
      "direction": "down",
      "time": "14:00",
      "timestamp": "2026-07-05T14:00:44.513384"
    },
    {
      "event_id": "211829",
      "title": "Will MrBeast get married by December 31?",
      "slug": "will-mrbeast-get-married-by-december-31",
      "prev_prob": 0.765,
      "curr_prob": 0.8,
      "threshold": 0.8,
      "direction": "up",
      "time": "21:00",
      "timestamp": "2026-07-05T21:00:54.097540"
    },
    {
      "event_id": "211829",
      "title": "Will MrBeast get married by December 31?",
      "slug": "will-mrbeast-get-married-by-december-31",
      "prev_prob": 0.8,
      "curr_prob": 0.765,
      "threshold": 0.8,
      "direction": "down",
      "time": "22:01",
      "timestamp": "2026-07-05T22:01:25.277074"
    },
    {
      "event_id": "333162",
      "title": "Which characters will appear in Avengers: Doomsday?",
      "slug": "which-characters-will-appear-in-avengers-doomsday",
      "prev_prob": 0.795,
      "curr_prob": 0.835,
      "threshold": 0.8,
      "direction": "up",
      "time": "22:01",
      "timestamp": "2026-07-05T22:01:25.277103"
    }
  ],
  "crossing_count": 5,
  "last_updated": "2026-07-05T22:01:25.277283"
}